{"directed": false, "multigraph": false, "graph": [], "nodes": [{"weight": 4, "label": true, "avg_deg": 3.009213040807099, "degree": 0.8, "id": 0}, {"weight": 4, "label": true, "avg_deg": 3.0117407067875854, "degree": 4.8, "id": 1}, {"weight": 3, "label": true, "avg_deg": 3.025708922149172, "degree": 3.75, "id": 2}, {"weight": 2, "label": true, "avg_deg": 3.025708922149172, "degree": 1.0, "id": 3}, {"weight": 1, "label": true, "avg_deg": 3.039677137510758, "degree": 0.45, "id": 4}, {"weight": 5, "label": true, "avg_deg": 3.058984103398778, "degree": 6.0, "id": 5}, {"weight": 4, "label": true, "avg_deg": 3.0644835835987174, "degree": 6.0, "id": 6}, {"weight": 3, "label": true, "avg_deg": 3.0644835835987174, "degree": 1.5, "id": 7}], "adjacency": [[{"length": 5, "id": 1}], [{"length": 5, "id": 0}, {"length": 1, "id": 2}], [{"length": 1, "id": 1}, {"length": 4, "id": 3}], [{"length": 4, "id": 2}, {"length": 4, "id": 4}], [{"length": 4, "id": 3}, {"length": 5, "id": 5}], [{"length": 5, "id": 4}, {"length": 1, "id": 6}], [{"length": 1, "id": 5}, {"length": 2, "id": 7}], [{"length": 2, "id": 6}]]}
